citymappingworld/__init__.py
citymappingworld/core.py
citymappingworld/worldcitymaster.json
worldcitymapping/__init__.py
worldcitymapping/core.py
worldcitymapping/worldcitymaster.json
citymappingworld-0.1.0.dist-info/METADATA
citymappingworld-0.1.0.dist-info/WHEEL
citymappingworld-0.1.0.dist-info/top_level.txt
citymappingworld-0.1.0.dist-info/RECORD
