Metadata-Version: 2.4
Name: citymappingworld
Version: 0.1.0
Summary: Returns city options with UTC offset, latitude and longitude from a JSON master list
Author: Ambuj Pratap Jain
License: MIT
Classifier: Programming Language :: Python :: 3
Classifier: Operating System :: OS Independent
Requires-Python: >=3.7
Dynamic: author
Dynamic: classifier
Dynamic: description-content-type
Dynamic: license
Dynamic: requires-python
Dynamic: summary
